pycosio/__init__.py
pycosio/io.py
pycosio/_core/__init__.py
pycosio/_core/compat.py
pycosio/_core/exceptions.py
pycosio/_core/functions_core.py
pycosio/_core/functions_io.py
pycosio/_core/functions_os.py
pycosio/_core/functions_os_path.py
pycosio/_core/functions_shutil.py
pycosio/_core/io_base.py
pycosio/_core/io_base_buffered.py
pycosio/_core/io_base_raw.py
pycosio/_core/io_base_system.py
pycosio/_core/io_file_system.py
pycosio/_core/io_random_write.py
pycosio/_core/storage_manager.py
pycosio/storage/__init__.py
pycosio/storage/azure.py
pycosio/storage/azure_file.py
pycosio/storage/http.py
pycosio/storage/oss.py
pycosio/storage/s3.py
pycosio/storage/swift.py
pycosio/storage/azure_blob/__init__.py
pycosio/storage/azure_blob/_append_blob.py
pycosio/storage/azure_blob/_base_blob.py
pycosio/storage/azure_blob/_block_blob.py
pycosio/storage/azure_blob/_page_blob.py
pycosio/storage/azure_blob/_system.py
pycosio-1.3.3.dist-info/LICENSE
pycosio-1.3.3.dist-info/METADATA
pycosio-1.3.3.dist-info/WHEEL
pycosio-1.3.3.dist-info/top_level.txt
pycosio-1.3.3.dist-info/zip-safe
pycosio-1.3.3.dist-info/RECORD
