Metadata-Version: 2.1
Name: pycosio
Version: 1.3.3
Summary: Python Cloud Object Storage I/O
Home-page: https://github.com/Accelize/pycosio
Author: Accelize
Author-email: info@accelize.com
License: Apache License, Version 2.0
Project-URL: Documentation, https://pycosio.readthedocs.io
Project-URL: Download, https://pypi.org/project/pycosio
Keywords: cloud cloud-storage bucket io stream
Platform: UNKNOWN
Classifier: Development Status :: 5 - Production/Stable
Classifier: Intended Audience :: Developers
Classifier: License :: OSI Approved :: Apache Software License
Classifier: Topic :: System :: Filesystems
Classifier: Programming Language :: Python
Classifier: Programming Language :: Python :: 2
Classifier: Programming Language :: Python :: 2.7
Classifier: Programming Language :: Python :: 3
Classifier: Programming Language :: Python :: 3.4
Classifier: Programming Language :: Python :: 3.5
Classifier: Programming Language :: Python :: 3.6
Classifier: Programming Language :: Python :: 3.7
Classifier: Operating System :: OS Independent
Requires-Python: >=2.7,!=3.0.*,!=3.1.*,!=3.2.*,!=3.3.*
Requires-Dist: requests (>=2.20.0)
Requires-Dist: python-dateutil (>=2.6.0)
Requires-Dist: scandir (>=1.5) ; python_version <= "3.4"
Requires-Dist: futures (>=3.1.1) ; python_version == "2.7"
Provides-Extra: all
Requires-Dist: azure-storage-blob (>=1.3.0) ; extra == 'all'
Requires-Dist: azure-storage-file (>=1.3.0) ; extra == 'all'
Requires-Dist: python-swiftclient[keystone] (>=3.3.0) ; extra == 'all'
Requires-Dist: oss2 (>=2.3.0) ; extra == 'all'
Requires-Dist: boto3 (>=1.5.0) ; extra == 'all'
Provides-Extra: azure_blob
Requires-Dist: azure-storage-blob (>=1.3.0) ; extra == 'azure_blob'
Provides-Extra: azure_file
Requires-Dist: azure-storage-file (>=1.3.0) ; extra == 'azure_file'
Provides-Extra: oss
Requires-Dist: oss2 (>=2.3.0) ; extra == 'oss'
Provides-Extra: s3
Requires-Dist: boto3 (>=1.5.0) ; extra == 's3'
Provides-Extra: swift
Requires-Dist: python-swiftclient[keystone] (>=3.3.0) ; extra == 'swift'
